<?xml version="1.0" encoding="UTF-8"?>
<objects serializationModel="Studio.02.03.00">
	<object class="AudioFile" id="{1f366253-ec25-43b7-9802-2684557765ca}">
		<property name="assetPath">
			<value>MUS/JINGLES/jingle_island_3_3.wav</value>
		</property>
		<property name="frequencyInKHz">
			<value>48</value>
		</property>
		<property name="channelCount">
			<value>2</value>
		</property>
		<property name="length">
			<value>6.97675</value>
		</property>
		<relationship name="masterAssetFolder">
			<destination>{139ecff4-c2b9-4cca-b847-163d826393ec}</destination>
		</relationship>
	</object>
</objects>
